inotipy.py
inotipy-0.1.1.dist-info/COPYING
inotipy-0.1.1.dist-info/METADATA
inotipy-0.1.1.dist-info/WHEEL
inotipy-0.1.1.dist-info/top_level.txt
inotipy-0.1.1.dist-info/RECORD
