Metadata-Version: 2.1
Name: inotipy
Version: 0.1.1
Summary: inotify for asyncio
Home-page: https://github.com/diefans/inotipy
Author: Oliver Berger
Author-email: diefans@gmail.com
License: GNU Lesser General Public License v2.1
Keywords: inotify asyncio
Platform: UNKNOWN
Classifier: Framework :: AsyncIO
Classifier: Programming Language :: Python :: 3 :: Only
Classifier: License :: OSI Approved :: GNU Lesser General Public License v2 or later (LGPLv2+)
